XorEncoder/Encoder.py
XorEncoder/__init__.py
XorEncoder-1.0.0.dist-info/LICENSE
XorEncoder-1.0.0.dist-info/METADATA
XorEncoder-1.0.0.dist-info/WHEEL
XorEncoder-1.0.0.dist-info/top_level.txt
XorEncoder-1.0.0.dist-info/RECORD
